[
  {
    "id": 100001757,
    "full_name": "Vergara, Michael Ronan M.",
    "email": "vergara.michael.ronan@gmail.com",
    "description": "Vi söker en nybörjarposition med färdigheter inom dataanalys och visualisering.",
    "resume": "100001757_Vergara_Michael_Ronan_M.pdf",
    "phone_number": "09493814966",
    "address": "Quezon City",
    "latest_degree": "BS Computer Science",
    "latest_university": "Adamson University",
    "current_company": "",
    "current_position": "",
    "current_position_description": "",
    "total_workexperience": "0 år 5 månader",
    "techterms": "Python, SQL, BigQuery, Java, C++",
    "expected_salary": 0,
    "expected_cost": 0
  }
]