[
  {
    "id": 100000097,
    "full_name": "Jeremy Rotoni",
    "email": "jeremy.rotoni@gmail.com",
    "description": "Frontend-utvecklare med 5 års erfarenhet av webbutveckling och leadgenerering.",
    "resume": "100000097_Jeremy_Rotoni.pdf",
    "phone_number": "09176323441",
    "address": "Taytay",
    "latest_degree": "Masters in Information Systems",
    "latest_university": "University of the Philippines Open University",
    "current_company": "TOA Global Manila",
    "current_position": "Frontend-utvecklare",
    "current_position_description": "Utveckla och underhålla webbplatser med hjälp av Shopify Liquid och React JS.",
    "total_workexperience": "11 år 4 månader",
    "techterms": "HTML,CSS,JavaScript,React,PHP",
    "expected_salary": 86250,
    "expected_cost": 28091
  },
  {
    "id": 100000108,
    "full_name": "Marissa R. Oco",
    "email": "ocomarissa@gmail.com",
    "description": "Software Engineer / NCLC-utvecklare med erfarenhet av full-stack webbutveckling och applikationsanalys.",
    "resume": "100000108_Marissa_R_Oco.pdf",
    "phone_number": "09778206477",
    "address": "",
    "latest_degree": "Masters in Information Technology",
    "latest_university": "AMA University",
    "current_company": "Accenture",
    "current_position": "Analytiker inom applikationsutveckling",
    "current_position_description": "Sammanställa och analysera data, processer och koder för att felsöka problem och identifiera områden som kan förbättras. Hjälpa till med att definiera och granska tekniska krav.",
    "total_workexperience": "13 år 8 månader",
    "techterms": "HTML,CSS,JavaScript,React,Node,Python",
    "expected_salary": 93750,
    "expected_cost": 29618
  },
  {
    "id": 100000124,
    "full_name": "Mark Christian Cabili Dacles",
    "email": "markdacles78@gmail.com",
    "description": "Web Development Specialist II med expertis inom att bygga och underhålla landningssidor och e-postmallar.",
    "resume": "100000124_Mark_Christian_Cabili_Dacles.pdf",
    "phone_number": "09204985036",
    "address": "San Juan City",
    "latest_degree": "Bachelor of Science in Information Technology",
    "latest_university": "PUP Sta.Mesa Manila",
    "current_company": "Straightarrow Corporation",
    "current_position": "Webbutvecklingsspecialist II",
    "current_position_description": "Ansvarig för att bygga och underhålla landningssidor och formulär, hantera inlämningar och skapa e-postmallar.",
    "total_workexperience": "4 år 5 månader",
    "techterms": "React,JavaScript,PHP,HTML,CSS",
    "expected_salary": 62500,
    "expected_cost": 23255
  }
]